authcodecatcher/__init__.py
authcodecatcher/cert.pem
authcodecatcher/server.py
authcodecatcher-0.1.1.dist-info/METADATA
authcodecatcher-0.1.1.dist-info/WHEEL
authcodecatcher-0.1.1.dist-info/licenses/LICENSE
authcodecatcher-0.1.1.dist-info/RECORD
