Metadata-Version: 2.1
Name: authcodecatcher
Version: 0.1.1
Summary: A server to catch Microsoft Entra OAuth codes and exchange them for a JWT token.
Project-URL: Homepage, https://github.com/hotnops/authcodecatcher
Author: hotnops
License-File: LICENSE
Requires-Python: >=3.10
Requires-Dist: pkce
Requires-Dist: pyjwt
Requires-Dist: requests
